filescope/__init__.py
filescope/manager.py
filescope-0.0.9.dist-info/LICENSE
filescope-0.0.9.dist-info/METADATA
filescope-0.0.9.dist-info/WHEEL
filescope-0.0.9.dist-info/top_level.txt
filescope-0.0.9.dist-info/RECORD
