Metadata-Version: 2.1
Name: filescope
Version: 0.0.9
Summary: Gerenciamento de arquivos em diretórios locais a partir de funcionalidades encapsuladas
Home-page: https://github.com/ThiagoPanini/filescope
Author: Thiago Panini
Author-email: thipanini94@gmail.com
License: MIT
Keywords: Files,directories,os,managing files
Platform: UNKNOWN
Classifier: Programming Language :: Python :: 3
Classifier: Development Status :: 3 - Alpha
Classifier: Environment :: Console
Classifier: Framework :: Jupyter
Classifier: Intended Audience :: Developers
Classifier: Natural Language :: Portuguese (Brazilian)
Classifier: License :: OSI Approved :: MIT License
Classifier: Operating System :: OS Independent
Classifier: Programming Language :: Python :: 3.6
Classifier: Programming Language :: Python :: 3.7
Classifier: Programming Language :: Python :: 3.8
Classifier: Programming Language :: Python :: 3.9
Classifier: Topic :: Software Development :: Libraries :: Python Modules
Requires-Python: >=3.0.0
Requires-Dist: pandas (==1.1.5)
Requires-Dist: matplotlib (==3.2.1)
Requires-Dist: seaborn (==0.11.1)
